setup.py
BiliCaptcha.egg-info/PKG-INFO
BiliCaptcha.egg-info/SOURCES.txt
BiliCaptcha.egg-info/dependency_links.txt
BiliCaptcha.egg-info/requires.txt
BiliCaptcha.egg-info/top_level.txt
bilicaptcha/__init__.py
bilicaptcha/cleanNoise.py
bilicaptcha/fetchSamples.py
bilicaptcha/misc.py
bilicaptcha/splitImage.py
bilicaptcha/unitTest.py