Metadata-Version: 1.0
Name: BiliCaptcha
Version: 0.0.4
Summary: Crack captcha when login on bilibili.com
Home-page: example.com
Author: buckle2000
Author-email: buckle2000@163.com
License: LGPL
Platform: UNKNOWN
